{
  "updated": "2026-03-03T01:05:47Z",
  "source_url": "https://www.jobindex.dk/",
  "categories": {
    "data analyst": [
      {
        "title": "Data Analyst for renewable energy value chain - DTU Chemical Engineering, DTU",
        "company": "Danmarks Tekniske Universitet",
        "location": "Lyngby",
        "url": "https://www.jobindex.dk/vis-job/h1640499",
        "posted": "2026-02-19",
        "snippet": "Data Analyst for renewable energy value chain - DTU Chemical Engineering\n\n        \n            Kgs. Lyngby\n            \n        \n\nIf you are looking to contribu",
        "source": "jobindex"
      },
      {
        "title": "AI Data Analyst",
        "company": "Telenor",
        "location": "Aalborg",
        "url": "https://www.jobindex.dk/vis-job/h1640060",
        "posted": "2026-02-18",
        "snippet": "AI Data Analyst\n\n        \n            Aalborg og mulighed for hjemmearbejde\n            \n        \n\nVil du være med til at analysere Telenors netværks- og kunded",
        "source": "jobindex"
      },
      {
        "title": "Finance Data Analyst",
        "company": "e-conomic",
        "location": "Denmark",
        "url": "https://www.jobindex.dk/vis-job/h1639996",
        "posted": "2026-02-18",
        "snippet": "Finance Data Analyst\n\n        \n            København V og mulighed for hjemmearbejde\n            \n        \n\nDu får en central rolle i at strukturere og videreud",
        "source": "jobindex"
      },
      {
        "title": "Master Data Analyst",
        "company": "Wrist Ship Supply",
        "location": "Denmark",
        "url": "https://www.jobindex.dk/vis-job/h1639743",
        "posted": "2026-02-17",
        "snippet": "Master Data Analyst\n\n        \n            Nørresundby\n            \n        \n\nPassionate about turning data into insight and bridging business and IT?You will pl",
        "source": "jobindex"
      },
      {
        "title": "Data Analyst for Molecular Endocrinology and Stem Cell Research Unit (KMEB)",
        "company": "Syddansk Universitet",
        "location": "KMEB",
        "url": "https://www.jobindex.dk/vis-job/r13655457",
        "posted": "2026-03-02",
        "snippet": "Data Analyst for Molecular Endocrinology and Stem Cell Research Unit (KMEB)\n\n\n        \n            Odense M\n            \n        \n\nWe are looking for a Data Ana",
        "source": "jobindex"
      },
      {
        "title": "TV 2 Data & Insight søger Advanced Data Analyst",
        "company": "TV 2 Danmark A/S",
        "location": "Denmark",
        "url": "https://www.jobindex.dk/vis-job/r13635624",
        "posted": "2026-02-19",
        "snippet": "TV 2 Data &amp; Insight søger Advanced Data Analyst\n\n\n        \n            København SV\n            \n        \n\nTV 2 Data &amp; Insight søger Advanced Data Analy",
        "source": "jobindex"
      },
      {
        "title": "Bliv dataanalytiker i Customer data i en foreningsejet Nykredit-koncern",
        "company": "Nykredit",
        "location": "Denmark",
        "url": "https://www.jobindex.dk/vis-job/h1641367",
        "posted": "2026-02-23",
        "snippet": "Bliv dataanalytiker i Customer data i en foreningsejet Nykredit-koncern\n\n        \n            Nordhavn\n            \n        \n\nMotiveres du af at arbejde med dat",
        "source": "jobindex"
      },
      {
        "title": "BI-Specialist & Dataanalytiker",
        "company": "Sorø Kommune",
        "location": "Denmark",
        "url": "https://www.jobindex.dk/vis-job/h1639507",
        "posted": "2026-02-16",
        "snippet": "BI-Specialist &amp; Dataanalytiker\n\n        \n            Sorø\n            \n        \n\nVil du være arkitekten bag vores datamodeller – og den, der gør resten af o",
        "source": "jobindex"
      },
      {
        "title": "Dataanalytiker til centerstaben i Center for Kræft og Organsygdomme (CKO) på Rigshospitalet",
        "company": "Region Hovedstaden",
        "location": "CKO",
        "url": "https://www.jobindex.dk/vis-job/r13629631",
        "posted": "2026-02-17",
        "snippet": "Dataanalytiker til centerstaben i Center for Kræft og Organsygdomme (CKO) på Rigshospitalet\n\n\n        \n            København Ø\n            \n        \n\nVil du vær",
        "source": "jobindex"
      }
    ],
    "business analyst": [
      {
        "title": "Business Analyst",
        "company": "ZF Danmark ApS",
        "location": "Taastrup",
        "url": "https://www.jobindex.dk/vis-job/h1642972",
        "posted": "2026-02-27",
        "snippet": "Business Analyst\n\n        \n            Taastrup\n            \n        \n\nEr du skarp til data, forretningsforståelse og procesoptimering – og trives du i rollen s",
        "source": "jobindex"
      },
      {
        "title": "Business Analyst til Finans",
        "company": "Tryg Forsikring A/S",
        "location": "Ballerup",
        "url": "https://www.jobindex.dk/vis-job/h1642702",
        "posted": "2026-02-27",
        "snippet": "Business Analyst til Finans\n\n        \n            Ballerup\n            \n        \n\nVil du være med dér, hvor finansielle indsigter bliver til strategiske beslutn",
        "source": "jobindex"
      },
      {
        "title": "Business Analyst",
        "company": "Solitwork A/S",
        "location": "Denmark",
        "url": "https://www.jobindex.dk/vis-job/h1627000",
        "posted": "2026-02-26",
        "snippet": "Business Analyst\n\n        \n            København K\n            \n        \n\nTrives du med at opbygge relationer til kunder, drive dialogen og identificere mulighe",
        "source": "jobindex"
      },
      {
        "title": "Business analyst (senior)",
        "company": "BEC Financial Technologies",
        "location": "senior",
        "url": "https://www.jobindex.dk/vis-job/h1641548",
        "posted": "2026-02-24",
        "snippet": "Business analyst (senior)\n\n        \n            Roskilde og mulighed for hjemmearbejde\n            \n        \n\nThe Senior Business Analyst role offers you the po",
        "source": "jobindex"
      },
      {
        "title": "Business analyst (Senior) – Core Banking",
        "company": "BEC Financial Technologies",
        "location": "Senior",
        "url": "https://www.jobindex.dk/vis-job/h1620714",
        "posted": "2026-02-24",
        "snippet": "Business analyst (Senior) – Core Banking\n\n        \n            Roskilde, possibility to work from home\n            \n        \n\nThe role offers a unique opportuni",
        "source": "jobindex"
      },
      {
        "title": "Business Analyst",
        "company": "Salling Group",
        "location": "Denmark",
        "url": "https://www.jobindex.dk/vis-job/h1641506",
        "posted": "2026-02-24",
        "snippet": "Business Analyst\n\n        \n            Køge\n            \n        \n\nVil du være en del af Danmarks største dagligvarekæde? I jobbet får du en bred berøringsflade",
        "source": "jobindex"
      },
      {
        "title": "Advanced Business Analyst - Bliv bindeled mellem AI-strategi og forretning i DSB",
        "company": "DSB",
        "location": "Taastrup",
        "url": "https://www.jobindex.dk/vis-job/h1641436",
        "posted": "2026-02-23",
        "snippet": "Advanced Business Analyst - Bliv bindeled mellem AI-strategi og forretning i DSB\n\n        \n            Taastrup og mulighed for hjemmearbejde",
        "source": "jobindex"
      },
      {
        "title": "AI Business Analyst",
        "company": "Akademikernes A-kasse",
        "location": "Denmark",
        "url": "https://www.jobindex.dk/vis-job/h1640789",
        "posted": "2026-02-20",
        "snippet": "AI Business Analyst\n\n        \n            København V\n            \n        \n\nVores mål er at skabe en sikker, compliant og skalerbar AI-platform, der kan hjælpe",
        "source": "jobindex"
      },
      {
        "title": "Senior Business Analyst for Customer Rating & Analytics",
        "company": "BEC Financial Technologies",
        "location": "Roskilde",
        "url": "https://www.jobindex.dk/vis-job/h1640294",
        "posted": "2026-02-19",
        "snippet": "Senior Business Analyst for Customer Rating &amp; Analytics\n\n        \n            Roskilde\n            \n        \n\nThis position is based at our friendly office",
        "source": "jobindex"
      },
      {
        "title": "Datadreven forretningsanalytiker",
        "company": "Politi",
        "location": "Glostrup",
        "url": "https://www.jobindex.dk/vis-job/h1640024",
        "posted": "2026-02-18",
        "snippet": "Datadreven forretningsanalytiker\n\n        \n            Glostrup\n            \n        \n\nI Center for Kommunikation og Udvikling søger vi lige nu en erfaren forre",
        "source": "jobindex"
      }
    ],
    "business intelligence": [
      {
        "title": "Business Intelligence Student Assistant",
        "company": "Everllence",
        "location": "Copenhagen",
        "url": "https://www.jobindex.dk/vis-job/h1641888",
        "posted": "2026-02-25",
        "snippet": "Business Intelligence Student Assistant\n\n        \n            Copenhagen, Hybrid position\n            \n        \n\nDo you have a strong financial understanding co",
        "source": "jobindex"
      },
      {
        "title": "Graduate, Data Engineer – Business Intelligence",
        "company": "Itm8",
        "location": "Denmark",
        "url": "https://www.jobindex.dk/vis-job/h1640818",
        "posted": "2026-02-20",
        "snippet": "Graduate, Data Engineer – Business Intelligence\n\n        \n            Viby J\n            \n        \n\nKickstart your IT career with itm8’s Graduate Program – an 1",
        "source": "jobindex"
      },
      {
        "title": "Graduate, Business Analytics – Business Intelligence",
        "company": "Itm8",
        "location": "Denmark",
        "url": "https://www.jobindex.dk/vis-job/h1640809",
        "posted": "2026-02-20",
        "snippet": "Graduate, Business Analytics – Business Intelligence\n\n        \n            Viby J\n            \n        \n\nKickstart your IT career with itm8’s Graduate Program –",
        "source": "jobindex"
      },
      {
        "title": "CRM & Business Intelligence Manager",
        "company": "Oxfam Danmark",
        "location": "Denmark",
        "url": "https://www.jobindex.dk/vis-job/h1638981",
        "posted": "2026-02-13",
        "snippet": "CRM &amp; Business Intelligence Manager\n\n        \n            København Ø og mulighed for hjemmearbejde\n            \n        \n\nVil du bruge dine evner inden for",
        "source": "jobindex"
      },
      {
        "title": "Studentermedhjælper til Business Intelligence",
        "company": "Normal A/S",
        "location": "Denmark",
        "url": "https://www.jobindex.dk/vis-job/h1638827",
        "posted": "2026-02-12",
        "snippet": "Studentermedhjælper til Business Intelligence\n\n        \n            Skanderborg\n            \n        \n\nBrænder du for data, og leder du efter et studiejob som e",
        "source": "jobindex"
      },
      {
        "title": "Senior Data Engineer",
        "company": "Systematic A/S",
        "location": "Aarhus",
        "url": "https://www.jobindex.dk/vis-job/h1637203",
        "posted": "2026-02-06",
        "snippet": "Senior Data Engineer\n\n        \n            Aarhus C\n            \n        \n\nSQL and Python back-end development, data modelling, creating sustainable data archit",
        "source": "jobindex"
      },
      {
        "title": "Senior Business Intelligence developer – develop dashboards to improve company efficiency",
        "company": "Systematic A/S",
        "location": "Aarhus",
        "url": "https://www.jobindex.dk/vis-job/h1637200",
        "posted": "2026-02-06",
        "snippet": "Senior Business Intelligence developer – develop dashboards to improve company efficiency\n\n        \n            Aarhus C\n            \n        \n\nCould you see yo",
        "source": "jobindex"
      },
      {
        "title": "Senior Business Intelligence Analyst",
        "company": "LEGO System A/S",
        "location": "Denmark",
        "url": "https://www.jobindex.dk/vis-job/r13656433",
        "posted": "2026-03-02",
        "snippet": "Senior Business Intelligence Analyst\n\n\n        \n            Billund\n            \n        \n\nAre you ready to play a crucial part in transforming data into action",
        "source": "jobindex"
      },
      {
        "title": "Data Engineer",
        "company": "Karnov Group Denmark A/S",
        "location": "Denmark",
        "url": "https://www.jobindex.dk/vis-job/h1642857",
        "posted": "2026-02-27",
        "snippet": "Data Engineer\n\n        \n            København K\n            \n        \n\nIf you enjoy hunting down why a number looks wrong, only to discover it was a single miss",
        "source": "jobindex"
      },
      {
        "title": "Senior Power BI Developer - Aarhus or Gdansk",
        "company": "Arla Foods amba",
        "location": "Aarhus",
        "url": "https://www.jobindex.dk/vis-job/h1638977",
        "posted": "2026-02-13",
        "snippet": "Senior Power BI Developer - Aarhus or Gdansk\n\n\nAre you ready to unfold your unique digital ?You will be the vital link between our Consumer Intelligence organiz",
        "source": "jobindex"
      },
      {
        "title": "Data Engineer (m/f/d)",
        "company": "Nacos Lyngsø Marine A/S",
        "location": "m/f/d",
        "url": "https://www.jobindex.dk/vis-job/h1637996",
        "posted": "2026-02-10",
        "snippet": "Data Engineer (m/​f/​d)\n\n        \n            Hørsholm\n            \n        \n\nWe are seeking a skilled Data Engineer to take end-to-end ownership of our on-prem",
        "source": "jobindex"
      },
      {
        "title": "Senior BI Developer",
        "company": "DANISH CROWN A/S",
        "location": "Randers",
        "url": "https://www.jobindex.dk/vis-job/h1637517",
        "posted": "2026-02-09",
        "snippet": "Senior BI Developer\n\n        \n            Randers SV\n            \n        \n\nYou will be at the forefront of our reporting strategy, by defining standards, model",
        "source": "jobindex"
      }
    ],
    "bi specialist": [
      {
        "title": "Lead Generation, AI & Business Intelligence Specialist",
        "company": "Contentway A/S",
        "location": "Denmark",
        "url": "https://www.jobindex.dk/vis-job/r13641332",
        "posted": "2026-02-23",
        "snippet": "Lead Generation, AI &amp; Business Intelligence Specialist\n\n\n        \n            København\n            \n        \n\nVil du have en rolle, hvor data, AI og analys",
        "source": "jobindex"
      },
      {
        "title": "Aller søger Business Intelligence Specialist - Group Finance",
        "company": "Aller A/S",
        "location": "Denmark",
        "url": "https://www.jobindex.dk/vis-job/r13622119",
        "posted": "2026-02-12",
        "snippet": "Aller søger Business Intelligence Specialist - Group Finance\n\n\n        \n            København V\n            \n        \n\nStillingen er nyoprettet og giver dig mul",
        "source": "jobindex"
      }
    ]
  }
}